navis/__init__.py
navis/__version__.py
navis/config.py
navis/conftest.py
navis/connectivity/__init__.py
navis/connectivity/adjacency.py
navis/connectivity/cnmetrics.py
navis/connectivity/matrix_utils.py
navis/connectivity/predict.py
navis/connectivity/similarity.py
navis/conversion/__init__.py
navis/conversion/converters.py
navis/conversion/meshing.py
navis/conversion/wrappers.py
navis/core/__init__.py
navis/core/base.py
navis/core/core_utils.py
navis/core/dotprop.py
navis/core/mesh.py
navis/core/neuronlist.py
navis/core/neurons.py
navis/core/skeleton.py
navis/core/volumes.py
navis/core/voxel.py
navis/data/__init__.py
navis/data/load_data.py
navis/data/meta.json
navis/data/readme.md
navis/data/gml/1734350788.gml
navis/data/gml/1734350908.gml
navis/data/gml/722817260.gml
navis/data/gml/754534424.gml
navis/data/gml/754538881.gml
navis/data/obj/1734350788.obj
navis/data/obj/1734350908.obj
navis/data/obj/722817260.obj
navis/data/obj/754534424.obj
navis/data/obj/754538881.obj
navis/data/swc/1734350788.swc
navis/data/swc/1734350908.swc
navis/data/swc/722817260.swc
navis/data/swc/754534424.swc
navis/data/swc/754538881.swc
navis/data/synapses/1734350788.csv
navis/data/synapses/1734350908.csv
navis/data/synapses/722817260.csv
navis/data/synapses/754534424.csv
navis/data/synapses/754538881.csv
navis/data/volumes/lh.obj
navis/data/volumes/neuropil.obj
navis/graph/__init__.py
navis/graph/clinic.py
navis/graph/converters.py
navis/graph/graph_utils.py
navis/interfaces/__init__.py
navis/interfaces/allen_celltypes.py
navis/interfaces/blender.py
navis/interfaces/cave_utils.py
navis/interfaces/cytoscape.py
navis/interfaces/h01.py
navis/interfaces/insectbrain_db.py
navis/interfaces/microns.py
navis/interfaces/neuprint.py
navis/interfaces/neuromorpho.py
navis/interfaces/r.py
navis/interfaces/vfb.py
navis/interfaces/neuron/__init__.py
navis/interfaces/neuron/comp.py
navis/interfaces/neuron/network.py
navis/interfaces/neuron/utils.py
navis/intersection/__init__.py
navis-1.9.1.dist-info/LICENSE
navis-1.9.1.dist-info/METADATA
navis-1.9.1.dist-info/WHEEL
navis-1.9.1.dist-info/top_level.txt
navis-1.9.1.dist-info/RECORD
