Metadata-Version: 2.1
Name: navis
Version: 1.9.1
Summary: Neuron Analysis and Visualization library
Home-page: https://navis-org.github.io/navis/
Author: Philipp Schlegel
Author-email: pms70@cam.ac.uk
License: GNU GPL V3
Project-URL: Documentation, https://navis-org.github.io/navis/
Project-URL: Source, https://github.com/navis-org/navis
Project-URL: Changelog, https://navis-org.github.io/navis/changelog/
Keywords: Neuron Analysis Visualization Morphometrics Morphology Anatomy Connectivity Transform Neuroscience NBLAST Skeletons SWC neuPrint
Classifier: Development Status :: 4 - Beta
Classifier: Intended Audience :: Science/Research
Classifier: Topic :: Scientific/Engineering :: Bio-Informatics
Classifier: License :: OSI Approved :: GNU General Public License v3 or later (GPLv3+)
Classifier: Programming Language :: Python :: 3
Classifier: Programming Language :: Python :: 3.9
Classifier: Programming Language :: Python :: 3.10
Classifier: Programming Language :: Python :: 3.11
Requires-Python: >=3.9,<4.0
License-File: LICENSE
Requires-Dist: h5py>=3.1
Requires-Dist: matplotlib>=3.9
Requires-Dist: morphops>=0.1.11
Requires-Dist: ncollpyde>=0.18
Requires-Dist: networkx>=2.4
Requires-Dist: numpy>=1.16
Requires-Dist: pandas>=1.0
Requires-Dist: pint>=0.10
Requires-Dist: pynrrd>=0.4.2
Requires-Dist: pypng>=0.0.18
Requires-Dist: requests>=2.20
Requires-Dist: seaborn>=0.10
Requires-Dist: setuptools>=65.5.1
Requires-Dist: scipy>=1.5
Requires-Dist: six>=1.11
Requires-Dist: tqdm>=4.45
Requires-Dist: typing-extensions>=3.7.4
Requires-Dist: trimesh>=3.8
Requires-Dist: fuzzywuzzy>=0.18
Requires-Dist: molesq>=0.2.0
Requires-Dist: rdata>=0.5
Requires-Dist: igraph!=0.10.0,!=0.10.1
Requires-Dist: skeletor>=1.0.0
Requires-Dist: pykdtree; platform_system != "Darwin"
Requires-Dist: pykdtree<=1.3.12; platform_system == "Darwin"
Provides-Extra: all
Requires-Dist: pathos>=0.2.7; extra == "all"
Requires-Dist: Shapely>=1.6.0; extra == "all"
Requires-Dist: xxhash; extra == "all"
Requires-Dist: cloud-volume>=5.2.0; extra == "all"
Requires-Dist: navis-fastcore>=0.0.7; extra == "all"
Requires-Dist: plotly>=4.9; extra == "all"
Requires-Dist: k3d; extra == "all"
Requires-Dist: vispy[pyside6]>=0.6.4; extra == "all"
Requires-Dist: jupyter-rfb>=0.4.1; extra == "all"
Requires-Dist: octarine3d[all]>=0.2.3; extra == "all"
Requires-Dist: octarine-navis-plugin>=0.1.2; extra == "all"
Requires-Dist: pyfqmr; extra == "all"
Provides-Extra: all-dev
Requires-Dist: pathos>=0.2.7; extra == "all-dev"
Requires-Dist: Shapely>=1.6.0; extra == "all-dev"
Requires-Dist: xxhash; extra == "all-dev"
Requires-Dist: cloud-volume>=5.2.0; extra == "all-dev"
Requires-Dist: navis-fastcore>=0.0.7; extra == "all-dev"
Requires-Dist: plotly>=4.9; extra == "all-dev"
Requires-Dist: k3d; extra == "all-dev"
Requires-Dist: vispy[pyside6]>=0.6.4; extra == "all-dev"
Requires-Dist: jupyter-rfb>=0.4.1; extra == "all-dev"
Requires-Dist: octarine3d[all]>=0.2.3; extra == "all-dev"
Requires-Dist: octarine-navis-plugin>=0.1.2; extra == "all-dev"
Requires-Dist: pyfqmr; extra == "all-dev"
Requires-Dist: jupyter; extra == "all-dev"
Requires-Dist: neuprint-python; extra == "all-dev"
Requires-Dist: caveclient; extra == "all-dev"
Requires-Dist: cloud-volume; extra == "all-dev"
Requires-Dist: flybrains; extra == "all-dev"
Requires-Dist: scikit-image; extra == "all-dev"
Requires-Dist: flake8; extra == "all-dev"
Requires-Dist: wheel; extra == "all-dev"
Requires-Dist: mypy; extra == "all-dev"
Requires-Dist: pytest; extra == "all-dev"
Requires-Dist: pytest-env; extra == "all-dev"
Requires-Dist: pytest-xvfb; extra == "all-dev"
Requires-Dist: pytest-timeout; extra == "all-dev"
Requires-Dist: gitpython; extra == "all-dev"
Requires-Dist: mkdocs; extra == "all-dev"
Requires-Dist: mkdocs-material[imaging]; extra == "all-dev"
Requires-Dist: mkdocs-gen-files; extra == "all-dev"
Requires-Dist: mkdocstrings[python]; extra == "all-dev"
Requires-Dist: mkdocs-glightbox; extra == "all-dev"
Requires-Dist: mkdocs-gallery; extra == "all-dev"
Requires-Dist: markdown-exec; extra == "all-dev"
Requires-Dist: mkdocs-section-index; extra == "all-dev"
Requires-Dist: mkdocs-literate-nav; extra == "all-dev"
Requires-Dist: mkdocs-minify-plugin; extra == "all-dev"
Requires-Dist: mkdocs-autorefs; extra == "all-dev"
Requires-Dist: mkdocs-macros-plugin; extra == "all-dev"
Requires-Dist: open3d; python_version < "3.12" and extra == "all-dev"
Requires-Dist: open3d; python_version < "3.12" and extra == "all"
Provides-Extra: cloudvolume
Requires-Dist: cloud-volume>=5.2.0; extra == "cloudvolume"
Provides-Extra: dev
Requires-Dist: flake8; extra == "dev"
Requires-Dist: wheel; extra == "dev"
Requires-Dist: mypy; extra == "dev"
Requires-Dist: pytest; extra == "dev"
Requires-Dist: pytest-env; extra == "dev"
Requires-Dist: pytest-xvfb; extra == "dev"
Requires-Dist: pytest-timeout; extra == "dev"
Requires-Dist: gitpython; extra == "dev"
Requires-Dist: scikit-image; extra == "dev"
Provides-Extra: docs
Requires-Dist: mkdocs; extra == "docs"
Requires-Dist: mkdocs-material[imaging]; extra == "docs"
Requires-Dist: mkdocs-gen-files; extra == "docs"
Requires-Dist: mkdocstrings[python]; extra == "docs"
Requires-Dist: mkdocs-glightbox; extra == "docs"
Requires-Dist: mkdocs-gallery; extra == "docs"
Requires-Dist: markdown-exec; extra == "docs"
Requires-Dist: mkdocs-section-index; extra == "docs"
Requires-Dist: mkdocs-literate-nav; extra == "docs"
Requires-Dist: mkdocs-minify-plugin; extra == "docs"
Requires-Dist: mkdocs-autorefs; extra == "docs"
Requires-Dist: mkdocs-macros-plugin; extra == "docs"
Provides-Extra: fastcore
Requires-Dist: navis-fastcore>=0.0.7; extra == "fastcore"
Provides-Extra: flybrains
Requires-Dist: flybrains; extra == "flybrains"
Provides-Extra: hash
Requires-Dist: xxhash; extra == "hash"
Provides-Extra: k3d
Requires-Dist: k3d; extra == "k3d"
Provides-Extra: meshes
Requires-Dist: pyfqmr; extra == "meshes"
Requires-Dist: open3d; python_version < "3.12" and extra == "meshes"
Provides-Extra: octarine-default
Requires-Dist: octarine3d[all]>=0.2.3; extra == "octarine-default"
Requires-Dist: octarine-navis-plugin>=0.1.2; extra == "octarine-default"
Provides-Extra: pathos
Requires-Dist: pathos>=0.2.7; extra == "pathos"
Provides-Extra: plotly
Requires-Dist: plotly>=4.9; extra == "plotly"
Provides-Extra: r
Requires-Dist: rpy2; extra == "r"
Provides-Extra: shapely
Requires-Dist: Shapely>=1.6.0; extra == "shapely"
Provides-Extra: test-notebook
Requires-Dist: jupyter; extra == "test-notebook"
Requires-Dist: neuprint-python; extra == "test-notebook"
Requires-Dist: caveclient; extra == "test-notebook"
Requires-Dist: cloud-volume; extra == "test-notebook"
Requires-Dist: flybrains; extra == "test-notebook"
Requires-Dist: scikit-image; extra == "test-notebook"
Requires-Dist: Shapely>=1.6.0; extra == "test-notebook"
Provides-Extra: vispy-default
Requires-Dist: vispy[pyside6]>=0.6.4; extra == "vispy-default"
Requires-Dist: jupyter-rfb>=0.4.1; extra == "vispy-default"
Provides-Extra: vispy-glfw
Requires-Dist: vispy[glfw]>=0.6.4; extra == "vispy-glfw"
Provides-Extra: vispy-pyglet
Requires-Dist: vispy[pyglet]>=0.6.4; extra == "vispy-pyglet"
Provides-Extra: vispy-pyqt5
Requires-Dist: vispy[pyqt5]>=0.6.4; extra == "vispy-pyqt5"
Provides-Extra: vispy-pyqt6
Requires-Dist: vispy[pyqt6]>=0.6.4; extra == "vispy-pyqt6"
Provides-Extra: vispy-pyside
Requires-Dist: vispy[pyside]>=0.6.4; extra == "vispy-pyside"
Provides-Extra: vispy-pyside2
Requires-Dist: vispy[pyside2]>=0.6.4; extra == "vispy-pyside2"
Provides-Extra: vispy-pyside6
Requires-Dist: vispy[pyside6]>=0.6.4; extra == "vispy-pyside6"
Provides-Extra: vispy-sdl2
Requires-Dist: vispy[sdl2]>=0.6.4; extra == "vispy-sdl2"
Provides-Extra: vispy-tk
Requires-Dist: vispy[tk]>=0.6.4; extra == "vispy-tk"
Provides-Extra: vispy-wx
Requires-Dist: vispy[wx]>=0.6.4; extra == "vispy-wx"
